python_package_size_uv/main.py
python_package_size_uv-0.5.2.dist-info/METADATA
python_package_size_uv-0.5.2.dist-info/WHEEL
python_package_size_uv-0.5.2.dist-info/entry_points.txt
python_package_size_uv-0.5.2.dist-info/RECORD
