Metadata-Version: 2.1
Name: python-package-size-uv
Version: 0.5.2
Summary: Learn after-install weight of any Python package including its dependencies.
Home-page: https://github.com/raayu83/python-package-size-uv
License: MIT
Author: Niklaus Stadler
Requires-Python: >=3.9.2,<3.13
Classifier: Development Status :: 5 - Production/Stable
Classifier: Intended Audience :: Developers
Classifier: Intended Audience :: Science/Research
Classifier: License :: OSI Approved :: MIT License
Classifier: Programming Language :: Python :: 3
Classifier: Programming Language :: Python :: 3.10
Classifier: Programming Language :: Python :: 3.11
Classifier: Programming Language :: Python :: 3.12
Requires-Dist: uv (>=0.2.18,<0.3.0)
Project-URL: Repository, https://github.com/raayu83/python-package-size-uv
